sigrok/__init__.py
sigrok/bindings.py
sigrok/bindings.pyi
sigrok/py.typed
sigrok/sigrok.py
sigrok/firmware/asix-sigma-100.fw
sigrok/firmware/asix-sigma-200.fw
sigrok/firmware/asix-sigma-50.fw
sigrok/firmware/asix-sigma-50sync.fw
sigrok/firmware/dreamsourcelab-dscope-fpga.fw
sigrok/firmware/dreamsourcelab-dscope-fx2.fw
sigrok/firmware/dreamsourcelab-dslogic-basic-fpga.fw
sigrok/firmware/dreamsourcelab-dslogic-basic-fx2.fw
sigrok/firmware/dreamsourcelab-dslogic-fpga-3v3.fw
sigrok/firmware/dreamsourcelab-dslogic-fpga-5v.fw
sigrok/firmware/dreamsourcelab-dslogic-fx2.fw
sigrok/firmware/dreamsourcelab-dslogic-plus-fpga.fw
sigrok/firmware/dreamsourcelab-dslogic-plus-fx2.fw
sigrok/firmware/dreamsourcelab-dslogic-pro-fpga.fw
sigrok/firmware/dreamsourcelab-dslogic-pro-fx2.fw
sigrok/firmware/fx2lafw-braintechnology-usb-lps.fw
sigrok/firmware/fx2lafw-cwav-usbeeax.fw
sigrok/firmware/fx2lafw-cwav-usbeedx.fw
sigrok/firmware/fx2lafw-cwav-usbeesx.fw
sigrok/firmware/fx2lafw-cwav-usbeezx.fw
sigrok/firmware/fx2lafw-cypress-fx2.fw
sigrok/firmware/fx2lafw-hantek-6022be.fw
sigrok/firmware/fx2lafw-hantek-6022bl.fw
sigrok/firmware/fx2lafw-hantek-pso2020.fw
sigrok/firmware/fx2lafw-instrustar-isds205b.fw
sigrok/firmware/fx2lafw-sainsmart-dds120.fw
sigrok/firmware/fx2lafw-saleae-logic.fw
sigrok/firmware/fx2lafw-sigrok-fx2-16ch.fw
sigrok/firmware/fx2lafw-sigrok-fx2-8ch.fw
sigrok/firmware/fx2lafw-yixingdianzi-mdso.fw
sigrok/firmware/sysclk-lwla1034-extneg.rbf
sigrok/firmware/sysclk-lwla1034-extpos.rbf
sigrok/firmware/sysclk-lwla1034-int.rbf
sigrok/firmware/sysclk-lwla1034-off.rbf
sigrok/include/fixes.h
sigrok/libsigrok-windows-i686/libsigrok.dll
sigrok/libsigrok-windows-i686/include/glib/galloca.h
sigrok/libsigrok-windows-i686/include/glib/garray.h
sigrok/libsigrok-windows-i686/include/glib/gasyncqueue.h
sigrok/libsigrok-windows-i686/include/glib/gatomic.h
sigrok/libsigrok-windows-i686/include/glib/gbacktrace.h
sigrok/libsigrok-windows-i686/include/glib/gbase64.h
sigrok-0.1.2.dist-info/METADATA
sigrok-0.1.2.dist-info/WHEEL
sigrok-0.1.2.dist-info/licenses/LICENSE
sigrok-0.1.2.dist-info/RECORD
