Metadata-Version: 2.4
Name: sigrok
Version: 0.1.2
Summary: Python-API for libsigrok
Project-URL: Homepage, https://github.com/stefanhoelzl/python-sigrok
Project-URL: Repository, https://github.com/stefanhoelzl/python-sigrok.git
Author-email: Stefan Hoelzl <stefan.hoelzl@posteo.de>
License-File: LICENSE
Classifier: Development Status :: 4 - Beta
Classifier: Intended Audience :: Developers
Classifier: Programming Language :: Python :: 3
Classifier: Programming Language :: Python :: 3.10
Classifier: Programming Language :: Python :: 3.11
Classifier: Programming Language :: Python :: 3.12
Classifier: Programming Language :: Python :: 3.13
Classifier: Topic :: Software Development :: Libraries
Classifier: Typing :: Typed
Requires-Python: >=3.10
Requires-Dist: pkgconfig>=1.5.5
Requires-Dist: platformdirs>=4.3.7
Requires-Dist: pyclibrary>=0.2.2
Requires-Dist: typing-extensions>=4.13.2
